{"include":[{"os":"macos-latest","r":"4.4"},{"os":"macos-latest","r":"4.3"},{"os":"windows-latest","r":"devel"},{"os":"windows-latest","r":"4.4"},{"os":"windows-latest","r":"4.3"},{"os":"ubuntu-22.04","r":"devel","http-user-agent":"release"},{"os":"ubuntu-22.04","r":"4.4"},{"os":"ubuntu-22.04","r":"4.3"},{"os":"ubuntu-22.04","r":"4.2"},{"os":"ubuntu-22.04","r":"4.1"},{"os":"ubuntu-22.04","r":"4.0"},{"os":"ubuntu-22.04","r":"4.4","covr":"true","desc":"with covr"},{"os":"macos-latest","r":"release","mysql_client":"false","RMARIADB_FORCE_MARIADBCONFIG":"1","RMARIADB_FORCE_MYSQLCONFIG":"NA","mysql_server":"NA","desc":"mariadb_config"},{"os":"macos-latest","r":"release","mysql_client":"true","RMARIADB_FORCE_MARIADBCONFIG":"NA","RMARIADB_FORCE_MYSQLCONFIG":"1","mysql_server":"NA","desc":"mysql_config"},{"os":"ubuntu-22.04","r":"release","mysql_client":"true","RMARIADB_FORCE_MARIADBCONFIG":"NA","RMARIADB_FORCE_MYSQLCONFIG":"NA","mysql_server":"true","desc":"MySQL server"},{"os":"ubuntu-22.04","r":"release","mysql_client":"true","RMARIADB_FORCE_MARIADBCONFIG":"NA","RMARIADB_FORCE_MYSQLCONFIG":"NA","mysql_server":"false","desc":"MariaDB server, MySQL client"},{"os":"ubuntu-22.04","r":"release","mysql_client":"false","RMARIADB_FORCE_MARIADBCONFIG":"NA","RMARIADB_FORCE_MYSQLCONFIG":"NA","mysql_server":"true","desc":"MySQL server, MariaDB client"},{"os":"ubuntu-22.04","r":"release","mysql_client":"false","RMARIADB_FORCE_MARIADBCONFIG":"NA","RMARIADB_FORCE_MYSQLCONFIG":"NA","mysql_server":"false","desc":"MariaDB server + client"}]}
